python_selenium_core/__init__.py
python_selenium_core/applications/__init__.py
python_selenium_core/applications/application.py
python_selenium_core/applications/core_service.py
python_selenium_core/applications/startup.py
python_selenium_core/configurations/__init__.py
python_selenium_core/configurations/base_configurations.py
python_selenium_core/configurations/element_cache_configuration.py
python_selenium_core/configurations/logger_configuration.py
python_selenium_core/configurations/retry_configuration.py
python_selenium_core/configurations/timeout_configuration.py
python_selenium_core/elements/__init__.py
python_selenium_core/elements/cached_element_state_provider.py
python_selenium_core/elements/core_element.py
python_selenium_core/elements/element_cache_handler.py
python_selenium_core/elements/element_factory.py
python_selenium_core/elements/element_finder.py
python_selenium_core/elements/element_state_provider.py
python_selenium_core/elements/constants/__init__.py
python_selenium_core/elements/constants/desired_state.py
python_selenium_core/elements/constants/element_state.py
python_selenium_core/elements/constants/elements_count.py
python_selenium_core/forms/__init__.py
python_selenium_core/localization/__init__.py
python_selenium_core/localization/localization_manager.py
python_selenium_core/localization/localized_logger.py
python_selenium_core/locator/__init__.py
python_selenium_core/locator/locator.py
python_selenium_core/logging/__init__.py
python_selenium_core/logging/logger.py
python_selenium_core/resources/settings.json
python_selenium_core/resources/localization/en.json
python_selenium_core/resources/localization/ru.json
python_selenium_core/utilities/__init__.py
python_selenium_core/utilities/action_retrier.py
python_selenium_core/utilities/element_action_retrier.py
python_selenium_core/utilities/environment_configuration.py
python_selenium_core/utilities/file_reader.py
python_selenium_core/utilities/json_settings_file.py
python_selenium_core-0.4.2.dist-info/LICENSE
python_selenium_core-0.4.2.dist-info/METADATA
python_selenium_core-0.4.2.dist-info/WHEEL
python_selenium_core-0.4.2.dist-info/top_level.txt
python_selenium_core-0.4.2.dist-info/zip-safe
python_selenium_core-0.4.2.dist-info/RECORD
