Metadata-Version: 2.1
Name: python-selenium-core
Version: 0.4.2
Summary: Selenium core for Python
Home-page: https://github.com/Polmik/python-selenium-core
Author: Egor Ryaboshapko
Author-email: mrpolmik@hotmail.com
Maintainer: Egor Ryaboshapko
Maintainer-email: mrpolmik@hotmail.com
Keywords: testing,selenium,driver,test automation
Platform: any
Classifier: Programming Language :: Python
Classifier: Programming Language :: Python :: 3.7
Classifier: Programming Language :: Python :: 3.8
Classifier: Programming Language :: Python :: 3.9
Classifier: Programming Language :: Python :: Implementation :: PyPy
Classifier: Framework :: Pytest
Classifier: Topic :: Software Development
Classifier: Topic :: Software Development :: Libraries
Classifier: Topic :: Software Development :: Libraries :: Python Modules
License-File: LICENSE
Requires-Dist: PyHamcrest ==1.9.0
Requires-Dist: pytest ==7.4.2
Requires-Dist: allure-pytest ==2.13.2
Requires-Dist: selenium ~=4.11.2
Requires-Dist: webdriver-manager ==4.0.0
Requires-Dist: dependency-injector ==4.41.0
